tutorial_package_eirini/__init__.py
tutorial_package_eirini/greet.py
tutorial_package_eirini-0.0.1.dist-info/DESCRIPTION.rst
tutorial_package_eirini-0.0.1.dist-info/METADATA
tutorial_package_eirini-0.0.1.dist-info/metadata.json
tutorial_package_eirini-0.0.1.dist-info/RECORD
tutorial_package_eirini-0.0.1.dist-info/top_level.txt
tutorial_package_eirini-0.0.1.dist-info/WHEEL
