Metadata-Version: 2.0
Name: tutorial-package-eirini
Version: 0.0.1
Summary: a demonstration how to create python packages
Home-page: UNKNOWN
Author: eirini
Author-email: UNKNOWN
License: BSD
Platform: UNKNOWN
